torchkin/__init__.py
torchkin/forward_kinematics.py
torchkin/joint.py
torchkin/robot.py
torchkin-0.1.1.dist-info/LICENSE
torchkin-0.1.1.dist-info/METADATA
torchkin-0.1.1.dist-info/WHEEL
torchkin-0.1.1.dist-info/top_level.txt
torchkin-0.1.1.dist-info/RECORD
