Metadata-Version: 2.1
Name: torchkin
Version: 0.1.1
Summary: Torch extension for differentiable kinematics.
Home-page: https://github.com/facebookresearch/theseus/lie
Author: Meta Research
Keywords: lie groups,differentiable optimization
Classifier: Programming Language :: Python :: 3
Classifier: License :: OSI Approved :: MIT License
Classifier: Intended Audience :: Science/Research
Classifier: Topic :: Scientific/Engineering :: Artificial Intelligence
Requires-Python: >=3.8
License-File: LICENSE
Requires-Dist: urdf-parser-py (>=0.0.4)
Requires-Dist: torchlie
